apisender/__init__.py
apisender/apisender.py
apisender-1.0.0b0.dist-info/LICENSE
apisender-1.0.0b0.dist-info/METADATA
apisender-1.0.0b0.dist-info/WHEEL
apisender-1.0.0b0.dist-info/top_level.txt
apisender-1.0.0b0.dist-info/RECORD
