Metadata-Version: 2.1
Name: apisender
Version: 1.0.0b0
Summary: Sends messages to various APIs for email or discord
Home-page: https://github.com/Sumiza/apisender/
Author: Sumiza
Author-email: sumiza@gmail.com
License: UNKNOWN
Project-URL: Bug Tracker, https://github.com/Sumiza/apisender/issues
Platform: UNKNOWN
Classifier: Programming Language :: Python :: 3.6
Classifier: Programming Language :: Python :: 3.7
Classifier: Programming Language :: Python :: 3.8
Classifier: Programming Language :: Python :: 3.9
Classifier: Programming Language :: Python :: 3.10
Classifier: License :: OSI Approved :: MIT License
Classifier: Operating System :: OS Independent
Requires-Python: >=3.6
License-File: LICENSE
Requires-Dist: requests
